{"type":"PR","pr":{"number":47,"head":"3366de2409902919c7480def4e46b82fe951f2c3"},"user":"天空之城","status":"draft","branch":"cms/2019-12-06-56-想与一班志同道合的朋友一起抗争奋斗，也能被叫一声“手足”！-glory-to-hongkong","collection":"posts","title":"56.想与一班志同道合的朋友一起抗争奋斗，也能被叫一声“手足”！ Glory To HongKong","description":"No Description!","objects":{"entry":{"path":"site/content/post/2019-12-06-56-想与一班志同道合的朋友一起抗争奋斗，也能被叫一声“手足”！-glory-to-hongkong.md","sha":"0406ba7a7a2a052357345d8eca58f2de58a42086"},"files":[]},"timeStamp":"2019-12-07T03:47:24.265Z"}